mabel/__init__.py
mabel/exceptions.py
mabel/version.py
mabel/adapters/__init__.py
mabel/adapters/disk/__init__.py
mabel/adapters/disk/disk_reader.py
mabel/adapters/disk/disk_writer.py
mabel/adapters/google/__init__.py
mabel/adapters/google/google_cloud_storage_reader.py
mabel/adapters/google/google_cloud_storage_reader_explicit_auth.py
mabel/adapters/google/google_cloud_storage_writer.py
mabel/adapters/minio/__init__.py
mabel/adapters/minio/minio_reader.py
mabel/adapters/minio/minio_writer.py
mabel/adapters/null/__init__.py
mabel/adapters/null/null_writer.py
mabel/data/__init__.py
mabel/data/internals/__init__.py
mabel/data/internals/collected_set.py
mabel/data/internals/dictset.cpython-37m-darwin.so
mabel/data/internals/dictset.py
mabel/data/internals/display.py
mabel/data/internals/dnf_filters.py
mabel/data/internals/dumb_iterator.py
mabel/data/internals/expression.cpython-37m-darwin.so
mabel/data/internals/expression.py
mabel/data/internals/group_by.cpython-37m-darwin.so
mabel/data/internals/group_by.py
mabel/data/internals/histogram.py
mabel/data/internals/index.py
mabel/data/internals/records.py
mabel/data/internals/xmler.py
mabel/data/internals/storage_classes/__init__.py
mabel/data/internals/storage_classes/base_storage_class.py
mabel/data/internals/storage_classes/storage_class_compressed_memory.py
mabel/data/internals/storage_classes/storage_class_disk.py
mabel/data/internals/storage_classes/storage_class_memory.py
mabel/data/readers/__init__.py
mabel/data/readers/reader.py
mabel/data/readers/internals/__init__.py
mabel/data/readers/internals/base_inner_reader.py
mabel/data/readers/internals/cursor.py
mabel/data/readers/internals/decompressors.py
mabel/data/readers/internals/inline_evaluator.cpython-37m-darwin.so
mabel/data/readers/internals/inline_evaluator.py
mabel/data/readers/internals/inline_functions.py
mabel/data/readers/internals/multiprocess_wrapper.py
mabel/data/readers/internals/parallel_reader.cpython-37m-darwin.so
mabelbeta-0.5.0a88.dist-info/LICENSE
mabelbeta-0.5.0a88.dist-info/METADATA
mabelbeta-0.5.0a88.dist-info/NOTICE
mabelbeta-0.5.0a88.dist-info/WHEEL
mabelbeta-0.5.0a88.dist-info/top_level.txt
mabelbeta-0.5.0a88.dist-info/RECORD
