Metadata-Version: 2.1
Name: mabelbeta
Version: 0.5.0a88
Summary: Python Data Libraries
Home-page: https://github.com/mabel-dev/mabel/
Author: joocer
Author-email: justin.joyce@joocer.com
Maintainer: Joocer
License: UNKNOWN
Platform: UNKNOWN
License-File: LICENSE
License-File: NOTICE
